[{"No":"87\n","Result":"Loss\n","Record":"60–24–3\n","Opponent":"Del Flanagan\n","Type":"TKO\n","Round_Time":"9 (10)\n","Date":"Mar 17, 1955\n","Age":"Auditorium, Saint Paul, Minnesota, U.S.\n","Locatin":"\n"},{"No":"86\n","Result":"Loss\n","Record":"60–23–3\n","Opponent":"Chico Varona\n","Type":"UD\n","Round_Time":"10\n","Date":"Oct 25, 1954\n","Age":"St. Nicholas Arena, Manhattan, New York City, New York, U.S.\n","Locatin":"\n"},{"No":"85\n","Result":"Loss\n","Record":"60–22–3\n","Opponent":"Johnny Saxton\n","Type":"UD\n","Round_Time":"10\n","Date":"Feb 24, 1954\n","Age":"Arena, Philadelphia, Pennsylvania, U.S.\n","Locatin":"\n"},{"No":"84\n","Result":"Loss\n","Record":"60–21–3\n","Opponent":"Kid Gavilán\n","Type":"UD\n","Round_Time":"15\n","Date":"Nov 13, 1953\n","Age":"Chicago Stadium, Chicago, Illinois, U.S.\n","Locatin":"For NYSAC, NBA, and The Ring welterweight titles\n"},{"No":"83\n","Result":"Win\n","Record":"60–20–3\n","Opponent":"Al Wilson\n","Type":"SD\n","Round_Time":"10\n","Date":"Oct 7, 1953\n","Age":"Coliseum, Baltimore, Maryland, U.S.\n","Locatin":"\n"},{"No":"82\n","Result":"Win\n","Record":"59–20–3\n","Opponent":"Danny Womber\n","Type":"UD\n","Round_Time":"10\n","Date":"Jun 9, 1953\n","Age":"Forum, Montreal, Quebec, Canada\n","Locatin":"\n"},{"No":"81\n","Result":"Win\n","Record":"58–20–3\n","Opponent":"Livio Minelli\n","Type":"UD\n","Round_Time":"10\n","Date":"May 7, 1953\n","Age":"Arena, Cleveland, Ohio, U.S.\n","Locatin":"\n"},{"No":"80\n","Result":"Win\n","Record":"57–20–3\n","Opponent":"Al Wilson\n","Type":"UD\n","Round_Time":"10\n","Date":"Apr 14, 1953\n","Age":"Ridgewood Grove, Brooklyn, New York City, New York, U.S.\n","Locatin":"\n"},{"No":"79\n","Result":"Win\n","Record":"56–20–3\n","Opponent":"Bobby Jones\n","Type":"KO\n","Round_Time":"5 (10)\n","Date":"Mar 20, 1953\n","Age":"Madison Square Garden, Manhattan, New York City, New York, U.S.\n","Locatin":"\n"},{"No":"78\n","Result":"Win\n","Record":"55–20–3\n","Opponent":"Jesús Portuguéz\n","Type":"KO\n","Round_Time":"5 (10)\n","Date":"Feb 23, 1953\n","Age":"Eastern Parkway Arena, Brooklyn, New York City, New York, U.S.\n","Locatin":"\n"},{"No":"77\n","Result":"Loss\n","Record":"54–20–3\n","Opponent":"Ralph Jones\n","Type":"UD\n","Round_Time":"10\n","Date":"Dec 5, 1952\n","Age":"Madison Square Garden, Manhattan, New York City, New York, U.S.\n","Locatin":"\n"},{"No":"76\n","Result":"Win\n","Record":"54–19–3\n","Opponent":"Joe Miceli\n","Type":"TKO\n","Round_Time":"8 (10)\n","Date":"Oct 31, 1952\n","Age":"Madison Square Garden, Manhattan, New York City, New York, U.S.\n","Locatin":"\n"},{"No":"75\n","Result":"Win\n","Record":"53–19–3\n","Opponent":"Ralph Zannelli\n","Type":"UD\n","Round_Time":"10\n","Date":"Sep 10, 1952\n","Age":"Olympia Stadium, Detroit, Michigan, U.S.\n","Locatin":"\n"},{"No":"74\n","Result":"Win\n","Record":"52–19–3\n","Opponent":"Irvin Steen\n","Type":"TKO\n","Round_Time":"3 (10)\n","Date":"Aug 25, 1952\n","Age":"Eastern Parkway Arena, Brooklyn, New York City, New York, U.S.\n","Locatin":"\n"},{"No":"73\n","Result":"Win\n","Record":"51–19–3\n","Opponent":"Laurent Dauthuille\n","Type":"TKO\n","Round_Time":"3 (10)\n","Date":"Jul 28, 1952\n","Age":"Forum, Montreal, Quebec, Canada\n","Locatin":"\n"},{"No":"72\n","Result":"Loss\n","Record":"50–19–3\n","Opponent":"Rocky Castellani\n","Type":"SD\n","Round_Time":"10\n","Date":"Jun 18, 1952\n","Age":"Chicago Stadium, Chicago, Illinois, U.S.\n","Locatin":"\n"},{"No":"71\n","Result":"Win\n","Record":"50–18–3\n","Opponent":"Del Flanagan\n","Type":"SD\n","Round_Time":"10\n","Date":"May 23, 1952\n","Age":"Madison Square Garden, Manhattan, New York City, New York, U.S.\n","Locatin":"\n"},{"No":"70\n","Result":"Win\n","Record":"49–18–3\n","Opponent":"Pierre Langlois\n","Type":"TKO\n","Round_Time":"4 (10)\n","Date":"May 1, 1952\n","Age":"Forum, Montreal, Quebec, Canada\n","Locatin":"\n"},{"No":"69\n","Result":"Loss\n","Record":"48–18–3\n","Opponent":"Rocky Castellani\n","Type":"UD\n","Round_Time":"10\n","Date":"Mar 28, 1952\n","Age":"Madison Square Garden, Manhattan, New York City, New York, U.S.\n","Locatin":"\n"},{"No":"68\n","Result":"Win\n","Record":"48–17–3\n","Opponent":"Vic Cardell\n","Type":"SD\n","Round_Time":"10\n","Date":"Feb 20, 1952\n","Age":"Chicago Stadium, Chicago, Illinois, U.S.\n","Locatin":"\n"},{"No":"67\n","Result":"Win\n","Record":"47–17–3\n","Opponent":"Bobby Rosado\n","Type":"KO\n","Round_Time":"8 (10)\n","Date":"Jan 28, 1952\n","Age":"Rhode Island Auditorium, Providence, Rhode Island, U.S.\n","Locatin":"\n"},{"No":"66\n","Result":"Win\n","Record":"46–17–3\n","Opponent":"Livio Minelli\n","Type":"SD\n","Round_Time":"10\n","Date":"Dec 27, 1951\n","Age":"Arena, Milwaukee, Wisconsin, U.S.\n","Locatin":"\n"},{"No":"65\n","Result":"Draw\n","Record":"45–17–3\n","Opponent":"Kid Gavilán\n","Type":"PTS\n","Round_Time":"10\n","Date":"Nov 28, 1951\n","Age":"Chicago Stadium, Chicago, Illinois, U.S.\n","Locatin":"\n"},{"No":"64\n","Result":"Win\n","Record":"45–17–2\n","Opponent":"Wilbur Wilson\n","Type":"KO\n","Round_Time":"8 (10)\n","Date":"Oct 15, 1951\n","Age":"Valley Arena, Holyoke, Massachusetts, U.S.\n","Locatin":"\n"},{"No":"63\n","Result":"Loss\n","Record":"44–17–2\n","Opponent":"Kid Gavilán\n","Type":"UD\n","Round_Time":"15\n","Date":"May 18, 1951\n","Age":"Madison Square Garden, Manhattan, New York City, New York, U.S.\n","Locatin":"Lost NBA welterweight title;For vacant NYSAC and The Ring welterweight titles\n"},{"No":"62\n","Result":"Win\n","Record":"44–16–2\n","Opponent":"Don Williams\n","Type":"TKO\n","Round_Time":"4 (10)\n","Date":"Apr 18, 1951\n","Age":"Olympia Stadium, Detroit, Michigan, U.S.\n","Locatin":"\n"},{"No":"61\n","Result":"Win\n","Record":"43–16–2\n","Opponent":"Charley Fusari\n","Type":"SD\n","Round_Time":"15\n","Date":"Mar 14, 1951\n","Age":"Chicago Stadium, Chicago,Illinois, U.S.\n","Locatin":"Won vacant NBA welterweight title\n"},{"No":"60\n","Result":"Win\n","Record":"42–16–2\n","Opponent":"Bobby Dykes\n","Type":"TKO\n","Round_Time":"1 (10)\n","Date":"Jan 24, 1951\n","Age":"Chicago Stadium, Chicago, Illinois, U.S.\n","Locatin":"\n"},{"No":"59\n","Result":"Win\n","Record":"41–16–2\n","Opponent":"Sammy Mastrean\n","Type":"KO\n","Round_Time":"3 (10)\n","Date":"Jan 9, 1951\n","Age":"Rainbo Arena, Chicago, Illinois, U.S.\n","Locatin":"\n"},{"No":"58\n","Result":"Win\n","Record":"40–16–2\n","Opponent":"Lester Felton\n","Type":"TKO\n","Round_Time":"3 (10)\n","Date":"Dec 13, 1950\n","Age":"Chicago Stadium, Chicago, Illinois, U.S.\n","Locatin":"\n"},{"No":"57\n","Result":"Loss\n","Record":"39–16–2\n","Opponent":"Holley Mims\n","Type":"UD\n","Round_Time":"10\n","Date":"Nov 27, 1950\n","Age":"Coliseum, Baltimore, Maryland, U.S.\n","Locatin":"\n"},{"No":"56\n","Result":"Win\n","Record":"39–15–2\n","Opponent":"Johnny Cesario\n","Type":"TKO\n","Round_Time":"3 (10)\n","Date":"Nov 22, 1950\n","Age":"St. Nicholas Arena, Manhattan, New York City, New York, U.S.\n","Locatin":"\n"},{"No":"55\n","Result":"Loss\n","Record":"38–15–2\n","Opponent":"Holley Mims\n","Type":"UD\n","Round_Time":"10\n","Date":"Nov 6, 1950\n","Age":"Coliseum, Baltimore, Maryland, U.S.\n","Locatin":"\n"},{"No":"54\n","Result":"Loss\n","Record":"38–14–2\n","Opponent":"Ike Williams\n","Type":"TKO\n","Round_Time":"8 (10)\n","Date":"Jan 20, 1950\n","Age":"Chicago Stadium, Chicago, Illinois, U.S.\n","Locatin":"\n"},{"No":"53\n","Result":"Win\n","Record":"38–13–2\n","Opponent":"Gene Hairston\n","Type":"TKO\n","Round_Time":"2 (10)\n","Date":"Jan 4, 1950\n","Age":"St. Nicholas Arena, Manhattan, New York City, New York, U.S.\n","Locatin":"\n"},{"No":"52\n","Result":"Win\n","Record":"37–13–2\n","Opponent":"Gaby Ferland\n","Type":"TKO\n","Round_Time":"2 (10)\n","Date":"Nov 18, 1949\n","Age":"Chicago Stadium, Chicago, Illinois, U.S.\n","Locatin":"\n"},{"No":"51\n","Result":"Win\n","Record":"36–13–2\n","Opponent":"Chuck Taylor\n","Type":"TKO\n","Round_Time":"2 (10)\n","Date":"Sep 15, 1949\n","Age":"Marigold Gardens Outdoor Arena, Chicago, Illinois, U.S.\n","Locatin":"\n"},{"No":"50\n","Result":"Win\n","Record":"35–13–2\n","Opponent":"Ramón Álvarez\n","Type":"TKO\n","Round_Time":"5 (10)\n","Date":"Apr 8, 1949\n","Age":"Chicago Stadium, Chicago, Illinois, U.S.\n","Locatin":"\n"},{"No":"49\n","Result":"Win\n","Record":"34–13–2\n","Opponent":"Frankie Vigeant\n","Type":"TKO\n","Round_Time":"4 (10)\n","Date":"Mar 29, 1949\n","Age":"Civic Auditorium, Seattle, Washington, U.S.\n","Locatin":"\n"},{"No":"48\n","Result":"Win\n","Record":"33–13–2\n","Opponent":"Chester Rico\n","Type":"TKO\n","Round_Time":"6 (10)\n","Date":"Feb 25, 1949\n","Age":"Chicago Stadium, Chicago, Illinois, U.S.\n","Locatin":"\n"},{"No":"47\n","Result":"Loss\n","Record":"32–13–2\n","Opponent":"Ike Williams\n","Type":"UD\n","Round_Time":"10\n","Date":"Jan 17, 1949\n","Age":"Arena, Philadelphia, Pennsylvania, U.S.\n","Locatin":"\n"},{"No":"46\n","Result":"Win\n","Record":"32–12–2\n","Opponent":"Melvin Bartholomew\n","Type":"PTS\n","Round_Time":"10\n","Date":"Jan 7, 1949\n","Age":"Coliseum Arena, New Orleans, Louisiana, U.S.\n","Locatin":"\n"},{"No":"45\n","Result":"Win\n","Record":"31–12–2\n","Opponent":"Joe Brown\n","Type":"KO\n","Round_Time":"4 (10)\n","Date":"Dec 3, 1948\n","Age":"Coliseum Arena, New Orleans, Louisiana, U.S.\n","Locatin":"\n"},{"No":"44\n","Result":"Draw\n","Record":"30–12–2\n","Opponent":"Bobby Lee\n","Type":"PTS\n","Round_Time":"10\n","Date":"Nov 29, 1948\n","Age":"Arena, Philadelphia, Pennsylvania, U.S.\n","Locatin":"\n"},{"No":"43\n","Result":"Loss\n","Record":"30–12–1\n","Opponent":"Bernard Docusen\n","Type":"UD\n","Round_Time":"10\n","Date":"Oct 29, 1948\n","Age":"Chicago Stadium, Chicago, Illinois, U.S.\n","Locatin":"\n"},{"No":"42\n","Result":"Win\n","Record":"30–11–1\n","Opponent":"Luigi Valentini\n","Type":"TKO\n","Round_Time":"7 (10)\n","Date":"Sep 15, 1948\n","Age":"Chicago Stadium, Chicago, Illinois, U.S.\n","Locatin":"\n"},{"No":"41\n","Result":"Win\n","Record":"29–11–1\n","Opponent":"Frankie Abrams\n","Type":"UD\n","Round_Time":"8\n","Date":"Jul 19, 1948\n","Age":"Marigold Gardens, Chicago, Illinois, U.S.\n","Locatin":"\n"},{"No":"40\n","Result":"Win\n","Record":"28–11–1\n","Opponent":"Jackie Solomon\n","Type":"KO\n","Round_Time":"1 (10)\n","Date":"Jul 6, 1948\n","Age":"Marigold Gardens, Chicago, Illinois, U.S.\n","Locatin":"\n"},{"No":"39\n","Result":"Loss\n","Record":"27–11–1\n","Opponent":"Beau Jack\n","Type":"TKO\n","Round_Time":"8 (10)\n","Date":"Jan 23, 1948\n","Age":"Chicago Stadium, Chicago, Illinois, U.S.\n","Locatin":"\n"},{"No":"38\n","Result":"Loss\n","Record":"27–10–1\n","Opponent":"Livio Minelli\n","Type":"SD\n","Round_Time":"10\n","Date":"Jan 5, 1948\n","Age":"Convention Hall, Philadelphia, Pennsylvania, U.S.\n","Locatin":"\n"},{"No":"37\n","Result":"Win\n","Record":"27–9–1\n","Opponent":"Phil Palmer\n","Type":"TKO\n","Round_Time":"7 (10)\n","Date":"Nov 12, 1947\n","Age":"Chicago Stadium, Chicago, Illinois, U.S.\n","Locatin":"\n"},{"No":"36\n","Result":"Loss\n","Record":"26–9–1\n","Opponent":"Gene Burton\n","Type":"UD\n","Round_Time":"10\n","Date":"Oct 6, 1947\n","Age":"Chicago Stadium, Chicago, Illinois, U.S.\n","Locatin":"\n"},{"No":"35\n","Result":"Win\n","Record":"26–8–1\n","Opponent":"Herbie Jones\n","Type":"KO\n","Round_Time":"8 (10)\n","Date":"Aug 4, 1947\n","Age":"Griffith Stadium, Washington, D.C., U.S.\n","Locatin":"\n"},{"No":"34\n","Result":"Loss\n","Record":"25–8–1\n","Opponent":"Gene Burton\n","Type":"UD\n","Round_Time":"10\n","Date":"Jun 6, 1947\n","Age":"Chicago Stadium, Chicago, Illinois, U.S.\n","Locatin":"\n"},{"No":"33\n","Result":"Loss\n","Record":"25–7–1\n","Opponent":"Sammy Angott\n","Type":"UD\n","Round_Time":"10\n","Date":"May 16, 1947\n","Age":"Chicago Stadium, Chicago, Illinois, U.S.\n","Locatin":"\n"},{"No":"32\n","Result":"Win\n","Record":"25–6–1\n","Opponent":"Danny Kapilow\n","Type":"SD\n","Round_Time":"10\n","Date":"Feb 18, 1947\n","Age":"Chicago Stadium, Chicago, Illinois, U.S.\n","Locatin":"\n"},{"No":"31\n","Result":"Win\n","Record":"24–6–1\n","Opponent":"Morris Reif\n","Type":"UD\n","Round_Time":"10\n","Date":"Jan 24, 1947\n","Age":"Chicago Stadium, Chicago, Illinois, U.S.\n","Locatin":"\n"},{"No":"30\n","Result":"Win\n","Record":"23–6–1\n","Opponent":"Willie Joyce\n","Type":"UD\n","Round_Time":"10\n","Date":"Dec 20, 1946\n","Age":"Chicago Stadium, Chicago, Illinois, U.S.\n","Locatin":"\n"},{"No":"29\n","Result":"Win\n","Record":"22–6–1\n","Opponent":"Willie Joyce\n","Type":"SD\n","Round_Time":"10\n","Date":"Oct 31, 1946\n","Age":"Chicago Stadium, Chicago, Illinois, U.S.\n","Locatin":"\n"},{"No":"28\n","Result":"Win\n","Record":"21–6–1\n","Opponent":"Richard Polite\n","Type":"TKO\n","Round_Time":"3 (10)\n","Date":"Oct 18, 1946\n","Age":"Pelican Stadium, New Orleans, Louisiana, U.S.\n","Locatin":"\n"},{"No":"27\n","Result":"Win\n","Record":"20–6–1\n","Opponent":"Eddie Lander\n","Type":"UD\n","Round_Time":"10\n","Date":"Sep 23, 1946\n","Age":"Marigold Gardens Outdoor Arena, Chicago, Illinois, U.S.\n","Locatin":"\n"},{"No":"26\n","Result":"Win\n","Record":"19–6–1\n","Opponent":"Roy Cadle\n","Type":"TKO\n","Round_Time":"5 (12)\n","Date":"Aug 14, 1946\n","Age":"Comiskey Park, Chicago, Illinois, U.S.\n","Locatin":"\n"},{"No":"25\n","Result":"Win\n","Record":"18–6–1\n","Opponent":"Bill Eddy\n","Type":"MD\n","Round_Time":"10\n","Date":"Aug 1, 1946\n","Age":"Rainbo Arena, Chicago, Illinois, U.S.\n","Locatin":"\n"},{"No":"24\n","Result":"Win\n","Record":"17–6–1\n","Opponent":"Pedro Firpo\n","Type":"KO\n","Round_Time":"1 (10)\n","Date":"May 3, 1946\n","Age":"Coliseum Arena, New Orleans, Louisiana, U.S.\n","Locatin":"\n"},{"No":"23\n","Result":"Win\n","Record":"16–6–1\n","Opponent":"Freddie Dawson\n","Type":"UD\n","Round_Time":"10\n","Date":"Apr 12, 1946\n","Age":"Chicago Stadium, Chicago, Illinois, U.S.\n","Locatin":"\n"},{"No":"22\n","Result":"Loss\n","Record":"15–6–1\n","Opponent":"Ike Williams\n","Type":"PTS\n","Round_Time":"10\n","Date":"Jan 20, 1946\n","Age":"Coliseum Arena, New Orleans, Louisiana, U.S.\n","Locatin":"\n"},{"No":"21\n","Result":"Loss\n","Record":"15–5–1\n","Opponent":"Chalky Wright\n","Type":"UD\n","Round_Time":"10\n","Date":"Dec 14, 1945\n","Age":"Coliseum Arena, New Orleans, Louisiana, U.S.\n","Locatin":"\n"},{"No":"20\n","Result":"Win\n","Record":"15–4–1\n","Opponent":"Cleo Shans\n","Type":"PTS\n","Round_Time":"10\n","Date":"Nov 11, 1945\n","Age":"Coliseum Arena, New Orleans, Louisiana, U.S.\n","Locatin":"\n"},{"No":"19\n","Result":"Draw\n","Record":"14–4–1\n","Opponent":"Cleo Shans\n","Type":"PTS\n","Round_Time":"10\n","Date":"Nov 2, 1945\n","Age":"Coliseum Arena, New Orleans, Louisiana, U.S.\n","Locatin":"\n"},{"No":"18\n","Result":"Win\n","Record":"14–4\n","Opponent":"Candy McDaniels\n","Type":"TKO\n","Round_Time":"6 (10)\n","Date":"Oct 26, 1945\n","Age":"Coliseum Arena, New Orleans, Louisiana, U.S.\n","Locatin":"\n"},{"No":"17\n","Result":"Loss\n","Record":"13–4\n","Opponent":"Dave Castilloux\n","Type":"PTS\n","Round_Time":"10\n","Date":"Aug 10, 1945\n","Age":"Auditorium, Milwaukee, Wisconsin, U.S.\n","Locatin":"\n"},{"No":"16\n","Result":"Loss\n","Record":"13–3\n","Opponent":"Joey Barnum\n","Type":"UD\n","Round_Time":"8\n","Date":"Jul 30, 1945\n","Age":"Marigold Gardens Outdoor Arena, Chicago, Illinois, U.S.\n","Locatin":"\n"},{"No":"15\n","Result":"Win\n","Record":"13–2\n","Opponent":"Melvin Johnson\n","Type":"PTS\n","Round_Time":"8\n","Date":"Jul 20, 1945\n","Age":"White City Arena, Chicago, Illinois, U.S.\n","Locatin":"\n"},{"No":"14\n","Result":"Win\n","Record":"12–2\n","Opponent":"Melvin Bartholomew\n","Type":"KO\n","Round_Time":"4 (10)\n","Date":"May 14, 1945\n","Age":"Marigold Gardens, Chicago, Illinois, U.S.\n","Locatin":"\n"},{"No":"13\n","Result":"Win\n","Record":"11–2\n","Opponent":"Patsy Spataro\n","Type":"PTS\n","Round_Time":"8\n","Date":"Mar 26, 1945\n","Age":"Chicago Stadium, Chicago, Illinois, U.S.\n","Locatin":"\n"},{"No":"12\n","Result":"Win\n","Record":"10–2\n","Opponent":"Jimmy Anest\n","Type":"PTS\n","Round_Time":"6\n","Date":"Feb 14, 1945\n","Age":"Chicago Stadium, Chicago, Illinois, U.S.\n","Locatin":"\n"},{"No":"11\n","Result":"Win\n","Record":"9–2\n","Opponent":"Robert Earl\n","Type":"TKO\n","Round_Time":"3 (8)\n","Date":"Jan 19, 1945\n","Age":"Chicago Stadium, Chicago, Illinois, U.S.\n","Locatin":"\n"},{"No":"10\n","Result":"Win\n","Record":"8–2\n","Opponent":"Ted Christie\n","Type":"TKO\n","Round_Time":"2 (8)\n","Date":"Dec 18, 1944\n","Age":"Marigold Gardens, Chicago, Illinois, U.S.\n","Locatin":"\n"},{"No":"9\n","Result":"Loss\n","Record":"7–2\n","Opponent":"Ace Miller\n","Type":"PTS\n","Round_Time":"8\n","Date":"Dec 4, 1944\n","Age":"Marigold Gardens, Chicago, Illinois, U.S.\n","Locatin":"\n"},{"No":"8\n","Result":"Win\n","Record":"7–1\n","Opponent":"Gene Spencer\n","Type":"PTS\n","Round_Time":"8\n","Date":"Nov 24, 1944\n","Age":"Chicago Stadium, Chicago, Illinois, U.S.\n","Locatin":"\n"},{"No":"7\n","Result":"Win\n","Record":"6–1\n","Opponent":"Gene Spencer\n","Type":"SD\n","Round_Time":"8\n","Date":"Oct 9, 1944\n","Age":"Marigold Gardens Outdoor Arena, Chicago, Illinois, U.S.\n","Locatin":"\n"},{"No":"6\n","Result":"Loss\n","Record":"5–1\n","Opponent":"Gene Spencer\n","Type":"UD\n","Round_Time":"8\n","Date":"Sep 25, 1944\n","Age":"Marigold Gardens Outdoor Arena, Chicago, Illinois, U.S.\n","Locatin":"\n"},{"No":"5\n","Result":"Win\n","Record":"5–0\n","Opponent":"Ted Christie\n","Type":"PTS\n","Round_Time":"8\n","Date":"Aug 7, 1944\n","Age":"Marigold Gardens Outdoor Arena, Chicago, Illinois, U.S.\n","Locatin":"\n"},{"No":"4\n","Result":"Win\n","Record":"4–0\n","Opponent":"Walter Holba\n","Type":"TKO\n","Round_Time":"2 (5)\n","Date":"Jul 24, 1944\n","Age":"Marigold Gardens Outdoor Arena, Chicago, Illinois, U.S.\n","Locatin":"\n"},{"No":"3\n","Result":"Win\n","Record":"3–0\n","Opponent":"Alvin Jordan\n","Type":"KO\n","Round_Time":"4 (4)\n","Date":"Jul 7, 1944\n","Age":"Comiskey Park, Chicago, Illinois, U.S.\n","Locatin":"\n"},{"No":"2\n","Result":"Win\n","Record":"2–0\n","Opponent":"Larry Wright\n","Type":"TKO\n","Round_Time":"3 (4)\n","Date":"Jun 26, 1944\n","Age":"Marigold Gardens, Chicago, Illinois, U.S.\n","Locatin":"\n"},{"No":"1\n","Result":"Win\n","Record":"1–0\n","Opponent":"Doyle Hirt\n","Type":"PTS\n","Round_Time":"4\n","Date":"Jun 12, 1944\n","Age":"Marigold Gardens, Chicago, Illinois, U.S.\n","Locatin":"\n"}]